{
  "active_predictions_total": 27,
  "by_level_scan": {
    "itf": 27
  },
  "counters": {
    "fixture_skip_doubles_or_team": 93,
    "fixture_skip_live": 2,
    "fixture_skip_status_finished": 26,
    "fixture_skip_status_retired": 2,
    "fixtures_scanned": 146,
    "fixtures_with_output": 27
  },
  "date_start": "2026-06-19",
  "days_ahead": 1,
  "decision_counts_scan": {
    "BET": 9,
    "STRONG_BET": 18
  },
  "fixtures_total": 269,
  "generated_at": "2026-06-19T06:50:26+00:00",
  "new_added_to_predictions": 27,
  "new_candidates": 27,
  "notes": [
    "This is standalone: it scans all eligible API fixtures and odds, not only tennis value picks.",
    "Odds are average clean odds after removing bookmaker outliers.",
    "Form and H2H are stored as tracking fields only; they do not affect TLE probability in v1.",
    "Only BET and STRONG_BET rows are stored as active predictions."
  ],
  "odds_rules": {
    "max_odds_deviation_from_median": 0.12,
    "min_bookmakers_each_side": 3,
    "min_clean_bookmakers": 3,
    "odds_max": 4.5,
    "odds_min": 1.3,
    "pricing": "average odds after outlier removal"
  },
  "outputs": {
    "active_csv": "data/elo_standalone/active_predictions.csv",
    "predictions_json": "data/elo_standalone/predictions.json",
    "report_json": "data/reports/elo_standalone/predictions_report.json",
    "results_json": "data/elo_standalone/results.json"
  },
  "reason_counts_scan": {
    "pass_edge": 9,
    "pass_strong_edge": 18
  },
  "scan_rows": 27,
  "status": "ok"
}
