{
  "active_after": 0,
  "active_before": 20,
  "generated_at": "2026-06-19T23:37:50+00:00",
  "notes": [
    "Standalone settle uses API-Tennis get_fixtures and matches by event_key.",
    "Settled picks are removed from predictions.json.",
    "results.json is the ledger and keeps pending and settled tracked picks."
  ],
  "outputs": {
    "active_csv": "data/elo_standalone/active_predictions.csv",
    "predictions_json": "data/elo_standalone/predictions.json",
    "report_json": "data/reports/elo_standalone/settle_report.json",
    "results_csv": "data/elo_standalone/results.csv",
    "results_json": "data/elo_standalone/results.json",
    "results_md": "data/elo_standalone/results.md"
  },
  "roi_summary": {
    "hit_rate": 0.6,
    "losses": 8,
    "pending": 0,
    "roi": 0.077736,
    "settled": 20,
    "total_profit": 1.7685,
    "total_stake": 22.75,
    "total_tracked": 20,
    "w_l": "12-8",
    "wins": 12
  },
  "settle_counts": {
    "dates_fetched": 8,
    "fixtures_fetched": 2724,
    "settled_loss": 8,
    "settled_win": 12
  },
  "settled_this_run": 20,
  "source": "API-Tennis get_fixtures",
  "status": "ok"
}
