{
  "cache_path": "data/raw/api_tennis/players/api_players.json",
  "cache_total_after": 5267,
  "cache_with_full_name_after": 2603,
  "collect_stats": {
    "files_seen": 1,
    "raw_fixtures_seen": 103,
    "singles_fixtures_used": 98,
    "skipped_doubles_fixtures": 5
  },
  "counters": {
    "cache_existing_before": 5267,
    "candidate_player_ids": 192,
    "fetched": 3,
    "fetched_missing_full_name": 3,
    "to_fetch": 3
  },
  "date_filter": {
    "end_date": "2026-06-21",
    "start_date": "2026-06-21"
  },
  "errors": [],
  "generated_at": "2026-06-21T22:21:42+00:00",
  "method": "get_players",
  "outputs": {
    "cache": "data/raw/api_tennis/players/api_players.json",
    "raw_responses": "",
    "report": "data/reports/api_tennis/fetch_api_player_details_report.json"
  },
  "raw_files": {
    "2026-06-21.json": 103
  },
  "raw_results_dir": "data/raw/api_tennis/results",
  "sample_fetched": [
    {
      "player_bday": "17.06.2008",
      "player_country": "Brazil",
      "player_full_name": "",
      "player_key": "67510",
      "player_logo": "",
      "player_name": "P. Rodrigues Longobardi",
      "source": "api_tennis:get_players",
      "updated_at": "2026-06-21T22:21:41+00:00"
    },
    {
      "player_bday": "",
      "player_country": "",
      "player_full_name": "",
      "player_key": "104198",
      "player_logo": "",
      "player_name": "A. Ganchev",
      "source": "api_tennis:get_players",
      "updated_at": "2026-06-21T22:21:41+00:00"
    },
    {
      "player_bday": "",
      "player_country": "",
      "player_full_name": "",
      "player_key": "104199",
      "player_logo": "",
      "player_name": "A. Tolev",
      "source": "api_tennis:get_players",
      "updated_at": "2026-06-21T22:21:42+00:00"
    }
  ],
  "source": "api_tennis"
}
